jq_sdk/__init__.py
jq_sdk/heatmap.py
jq_sdk/pipeline/__init__.py
jq_sdk/pipeline/process_manager.py
jq_sdk/pipeline/realtime_pipeline.py
jq_sdk/processing/__init__.py
jq_sdk/processing/interpolation.py
jq_sdk/processing/stats.py
jq_sdk/processing/transform.py
jq_sdk/serial/__init__.py
jq_sdk/serial/comm.py
jq_sdk/serial/device.py
jq_sdk/serial/protocol.py
jq_sdk/visualization/__init__.py
jq_sdk/visualization/config.py
jq_sdk/visualization/realtime.py
jq_sdk-0.2.2.dist-info/licenses/LICENSE
jq_sdk-0.2.2.dist-info/METADATA
jq_sdk-0.2.2.dist-info/WHEEL
jq_sdk-0.2.2.dist-info/top_level.txt
jq_sdk-0.2.2.dist-info/RECORD
