Metadata-Version: 2.4
Name: jq-sdk
Version: 0.2.2
Summary: A comprehensive package for sensor data acquisition and visualization
Author-email: Hirkond <thd20x@gmail.com>
License-Expression: MIT
Project-URL: Homepage, https://github.com/yourusername/JQ-SDK
Project-URL: Repository, https://github.com/yourusername/JQ-SDK
Project-URL: Bug Tracker, https://github.com/yourusername/JQ-SDK/issues
Keywords: heatmap,visualization,plotly,matrix,data-visualization,serial,sensor,realtime
Classifier: Development Status :: 4 - Beta
Classifier: Intended Audience :: Developers
Classifier: Intended Audience :: Science/Research
Classifier: Programming Language :: Python :: 3
Classifier: Programming Language :: Python :: 3.7
Classifier: Programming Language :: Python :: 3.8
Classifier: Programming Language :: Python :: 3.9
Classifier: Programming Language :: Python :: 3.10
Classifier: Programming Language :: Python :: 3.11
Classifier: Programming Language :: Python :: 3.12
Classifier: Topic :: Scientific/Engineering :: Visualization
Requires-Python: >=3.7
License-File: LICENSE
Requires-Dist: numpy>=1.19.0
Requires-Dist: plotly>=5.0.0
Provides-Extra: serial
Requires-Dist: pyserial>=3.5; extra == "serial"
Requires-Dist: matplotlib>=3.3.0; extra == "serial"
Requires-Dist: scipy>=1.5.0; extra == "serial"
Provides-Extra: dev
Requires-Dist: pytest>=7.0.0; extra == "dev"
Requires-Dist: pytest-cov>=3.0.0; extra == "dev"
Requires-Dist: black>=22.0.0; extra == "dev"
Requires-Dist: flake8>=4.0.0; extra == "dev"
Provides-Extra: all
Requires-Dist: jq-sdk[serial]; extra == "all"
Dynamic: license-file
